{"transcript":"joː nɒpot kiːvaːn","exists":true,"definitions":["Köszönés, melyet a nap bármely szakaszában lehet használni, de leginkább nappal.","Udvarias üdvözlés, amikor valaki találkozik valakivel, vagy elköszön tőle."],"examples":["Jó napot kívánok, miben segíthetek?","Amikor belépett a boltba, hangosan mondta: Jó napot kívánok!","Jó napot kívánok, viszlát holnap!"],"lemma":"jó napot kíván","lemmaPos":"idiom","synonyms":["jó napot","szervusz","helló"],"number":"singular","source":"jó napot kíván"}